[
  {
    "id": 1,
    "scheduled": "07/09/2022",
    "test_type": "Test A",
    "client": "Graham Conner"
  },
  {
    "id": 2,
    "scheduled": "07/09/2022",
    "test_type": "Test c",
    "client": "Cantrell Buckner"
  },
  {
    "id": 3,
    "scheduled": "07/09/2022",
    "test_type": "Test A",
    "client": "Lola Meyer"
  },
  {
    "id": 4,
    "scheduled": "07/09/2022",
    "test_type": "Test A",
    "client": "Christian Crane"
  },
  {
    "id": 5,
    "scheduled": "07/09/2022",
    "test_type": "Test A",
    "client": "Lynn Riley"
  },
  {
    "id": 6,
    "scheduled": "07/09/2022",
    "test_type": "Test B",
    "client": "Dudley Wall"
  },
  {
    "id": 7,
    "scheduled": "07/09/2022",
    "test_type": "Test c",
    "client": "Rios Bowman"
  },
  {
    "id": 8,
    "scheduled": "07/09/2022",
    "test_type": "Test A",
    "client": "Cantu Whitaker"
  },
  {
    "id": 9,
    "scheduled": "07/09/2022",
    "test_type": "Test c",
    "client": "Bartlett Roy"
  },
  {
    "id": 10,
    "scheduled": "07/09/2022",
    "test_type": "Test B",
    "client": "Tanisha Langley"
  },
  {
    "id": 11,
    "scheduled": "07/09/2022",
    "test_type": "Test B",
    "client": "Avis Thompson"
  },
  {
    "id": 12,
    "scheduled": "07/09/2022",
    "test_type": "Test B",
    "client": "Booker Molina"
  },
  {
    "id": 13,
    "scheduled": "07/09/2022",
    "test_type": "Test B",
    "client": "Thompson Leblanc"
  },
  {
    "id": 14,
    "scheduled": "07/09/2022",
    "test_type": "Test B",
    "client": "Schroeder Cash"
  },
  {
    "id": 15,
    "scheduled": "07/09/2022",
    "test_type": "Test c",
    "client": "Ingrid Donaldson"
  },
  {
    "id": 16,
    "scheduled": "07/09/2022",
    "test_type": "Test A",
    "client": "Kathleen Goodman"
  },
  {
    "id": 17,
    "scheduled": "07/09/2022",
    "test_type": "Test B",
    "client": "Frye Hart"
  },
  {
    "id": 18,
    "scheduled": "07/09/2022",
    "test_type": "Test A",
    "client": "Shannon Maddox"
  },
  {
    "id": 19,
    "scheduled": "07/09/2022",
    "test_type": "Test c",
    "client": "Bruce Wilson"
  },
  {
    "id": 20,
    "scheduled": "07/09/2022",
    "test_type": "Test A",
    "client": "Stein Beck"
  },
  {
    "id": 21,
    "scheduled": "07/09/2022",
    "test_type": "Test c",
    "client": "Moore Rocha"
  },
  {
    "id": 22,
    "scheduled": "07/09/2022",
    "test_type": "Test A",
    "client": "Jacobs Sosa"
  },
  {
    "id": 23,
    "scheduled": "07/09/2022",
    "test_type": "Test A",
    "client": "Gwendolyn Bolton"
  },
  {
    "id": 24,
    "scheduled": "07/09/2022",
    "test_type": "Test c",
    "client": "Johnnie Guy"
  },
  {
    "id": 25,
    "scheduled": "07/09/2022",
    "test_type": "Test B",
    "client": "Myra Morse"
  },
  {
    "id": 26,
    "scheduled": "07/09/2022",
    "test_type": "Test B",
    "client": "Oliver Witt"
  },
  {
    "id": 27,
    "scheduled": "07/09/2022",
    "test_type": "Test c",
    "client": "Salinas Hardy"
  },
  {
    "id": 28,
    "scheduled": "07/09/2022",
    "test_type": "Test A",
    "client": "Tyson Calhoun"
  },
  {
    "id": 29,
    "scheduled": "07/09/2022",
    "test_type": "Test A",
    "client": "Milagros Vaughan"
  },
  {
    "id": 30,
    "scheduled": "07/09/2022",
    "test_type": "Test A",
    "client": "Debora Parrish"
  },
  {
    "id": 31,
    "scheduled": "07/09/2022",
    "test_type": "Test c",
    "client": "Adkins Bell"
  },
  {
    "id": 32,
    "scheduled": "07/09/2022",
    "test_type": "Test B",
    "client": "Avery Mcintyre"
  },
  {
    "id": 33,
    "scheduled": "07/09/2022",
    "test_type": "Test A",
    "client": "Conley Horne"
  },
  {
    "id": 34,
    "scheduled": "07/09/2022",
    "test_type": "Test c",
    "client": "Dale Mitchell"
  },
  {
    "id": 35,
    "scheduled": "07/09/2022",
    "test_type": "Test A",
    "client": "Larsen Joyce"
  },
  {
    "id": 36,
    "scheduled": "07/09/2022",
    "test_type": "Test c",
    "client": "Anastasia Wiley"
  },
  {
    "id": 37,
    "scheduled": "07/09/2022",
    "test_type": "Test c",
    "client": "Underwood Beach"
  },
  {
    "id": 38,
    "scheduled": "07/09/2022",
    "test_type": "Test B",
    "client": "Eileen Booker"
  },
  {
    "id": 39,
    "scheduled": "07/09/2022",
    "test_type": "Test c",
    "client": "Mandy Tate"
  },
  {
    "id": 40,
    "scheduled": "07/09/2022",
    "test_type": "Test c",
    "client": "Amie Spence"
  },
  {
    "id": 41,
    "scheduled": "07/09/2022",
    "test_type": "Test c",
    "client": "Barry Barnes"
  },
  {
    "id": 42,
    "scheduled": "07/09/2022",
    "test_type": "Test c",
    "client": "Harrell Moore"
  }
]